odoo/addons/mrp_bom_component_menu/README.rst
odoo/addons/mrp_bom_component_menu/__init__.py
odoo/addons/mrp_bom_component_menu/__manifest__.py
odoo/addons/mrp_bom_component_menu/i18n/de.po
odoo/addons/mrp_bom_component_menu/i18n/mrp_bom_component_menu.pot
odoo/addons/mrp_bom_component_menu/static/description/icon.png
odoo/addons/mrp_bom_component_menu/views/mrp_bom_component_view.xml
odoo11_addon_mrp_bom_component_menu-11.0.1.0.0.99.dev3.dist-info/METADATA
odoo11_addon_mrp_bom_component_menu-11.0.1.0.0.99.dev3.dist-info/RECORD
odoo11_addon_mrp_bom_component_menu-11.0.1.0.0.99.dev3.dist-info/WHEEL
odoo11_addon_mrp_bom_component_menu-11.0.1.0.0.99.dev3.dist-info/top_level.txt
